Workbook

Sheet Fundamentals
A1: Date | B1: Revenue | C1: EBIT | D1: EBITDA | E1: D&A | F1: Tax Expense | G1: Interest Exp | H1: Net Income | I1: Total Debt | J1: Cash & Equiv | K1: Minority Int | L1: Shares Out | M1: Book Equity | N1: Total Assets | O1: CapEx | P1: FCF | Q1: Chg in NWC | S1: Start Year: | T1: 2019
A2: Ticker | B2: NESN SW Equity | C2: =$B$2 -> NESN SW Equity | D2: =$B$2 -> NESN SW Equity | E2: =$B$2 -> NESN SW Equity | F2: =$B$2 -> NESN SW Equity | G2: =$B$2 -> NESN SW Equity | H2: =$B$2 -> NESN SW Equity | I2: =$B$2 -> NESN SW Equity | J2: =$B$2 -> NESN SW Equity | ... R2: =$B$2 -> NESN SW Equity | S2: End Year: | T2: 2024
A3: Field | B3: SALES_REV_TURN | C3: IS_OPER_INC | D3: EBITDA | E3: CF_DEPR_AMORT | F3: IS_INC_TAX_EXP | G3: IS_INT_EXPENSE | H3: NET_INCOME | I3: SHORT_AND_LONG_TERM_DEBT | J3: BS_CASH_NEAR_CASH_ITEM | K3: IS_MINORITY_INTEREST_ADJUSTED | L3: BS_SH_OUT | M3: TOT_COMMON_EQY | N3: BS_TOT_ASSET | O3: CF_CAP_EXPEND_PRPTY_ADD | P3: CF_FREE_CASH_FLOW | Q3: CHNG_WORK_CAP | S3: To change range:
A4: BBG LIVE — Each cell = own BDH, fix date, no spill | S4: 1. Update years above
A5: Year | B5: Revenue | C5: EBIT | D5: EBITDA | E5: D&A | F5: Tax Expense | G5: Interest Exp | H5: Net Income | I5: Total Debt | J5: Cash & Equiv | K5: Minority Int | L5: Shares Out | M5: Book Equity | N5: Total Assets | O5: CapEx | P5: CFO | Q5: Chg in NWC | S5: 2. Change year in col A
A6: =$T$1 -> 2019 | B6: {=_xll.BDH(B$2,B$3,$A6&"1231",$A6&"1231","Fill=NA","Days=A")} -> 47251 | C6: {=_xll.BDH(C$2,C$3,$A6&"1231",$A6&"1231","Fill=NA","Days=A")} -> 9344 | D6: {=_xll.BDH(D$2,D$3,$A6&"1231",$A6&"1231","Fill=NA","Days=A")} -> 11193 | E6: {=_xll.BDH(E$2,E$3,$A6&"1231",$A6&"1231","Fill=NA","Days=A")} -> 1849 | F6: {=_xll.BDH(F$2,F$3,$A6&"1231",$A6&"1231","Fill=NA","Days=A")} -> 1448 | G6: {=_xll.BDH(G$2,G$3,$A6&"1231",$A6&"1231","Fill=NA","Days=A")} -> 510 | H6: {=_xll.BDH(H$2,H$3,$A6&"1231",$A6&"1231","Fill=NA","Days=A")} -> 7637 | I6: {=_xll.BDH(I$2,I$3,$A6&"1231",$A6&"1231","Fill=NA","Days=A")} -> 37164 | ... Q6: {=_xll.BDH(Q$2,Q$3,$A6&"1231",$A6&"1231","Fill=NA","Days=A")} -> 3697 | S6: 3. Copy BDH formula from row above
A7: =A6+1 -> 2020 | B7: {=_xll.BDH(B$2,B$3,$A7&"1231",$A7&"1231","Fill=NA","Days=A")} -> 43378 | C7: {=_xll.BDH(C$2,C$3,$A7&"1231",$A7&"1231","Fill=NA","Days=A")} -> 6963 | D7: {=_xll.BDH(D$2,D$3,$A7&"1231",$A7&"1231","Fill=NA","Days=A")} -> 8720 | E7: {=_xll.BDH(E$2,E$3,$A7&"1231",$A7&"1231","Fill=NA","Days=A")} -> 1757 | F7: {=_xll.BDH(F$2,F$3,$A7&"1231",$A7&"1231","Fill=NA","Days=A")} -> 1367 | G7: {=_xll.BDH(G$2,G$3,$A7&"1231",$A7&"1231","Fill=NA","Days=A")} -> 351 | H7: {=_xll.BDH(H$2,H$3,$A7&"1231",$A7&"1231","Fill=NA","Days=A")} -> 6349 | I7: {=_xll.BDH(I$2,I$3,$A7&"1231",$A7&"1231","Fill=NA","Days=A")} -> 39339 | ... Q7: {=_xll.BDH(Q$2,Q$3,$A7&"1231",$A7&"1231","Fill=NA","Days=A")} -> 3931
A8: =A7+1 -> 2021 | B8: {=_xll.BDH(B$2,B$3,$A8&"1231",$A8&"1231","Fill=NA","Days=A")} -> 45544 | C8: {=_xll.BDH(C$2,C$3,$A8&"1231",$A8&"1231","Fill=NA","Days=A")} -> 4813 | D8: {=_xll.BDH(D$2,D$3,$A8&"1231",$A8&"1231","Fill=NA","Days=A")} -> 6582 | E8: {=_xll.BDH(E$2,E$3,$A8&"1231",$A8&"1231","Fill=NA","Days=A")} -> 1769 | F8: {=_xll.BDH(F$2,F$3,$A8&"1231",$A8&"1231","Fill=NA","Days=A")} -> 1140 | G8: {=_xll.BDH(G$2,G$3,$A8&"1231",$A8&"1231","Fill=NA","Days=A")} -> 372 | H8: {=_xll.BDH(H$2,H$3,$A8&"1231",$A8&"1231","Fill=NA","Days=A")} -> 10960 | I8: {=_xll.BDH(I$2,I$3,$A8&"1231",$A8&"1231","Fill=NA","Days=A")} -> 45816 | ... Q8: {=_xll.BDH(Q$2,Q$3,$A8&"1231",$A8&"1231","Fill=NA","Days=A")} -> 6799
A9: =A8+1 -> 2022 | B9: {=_xll.BDH(B$2,B$3,$A9&"1231",$A9&"1231","Fill=NA","Days=A")} -> 49022 | C9: {=_xll.BDH(C$2,C$3,$A9&"1231",$A9&"1231","Fill=NA","Days=A")} -> 5707 | D9: {=_xll.BDH(D$2,D$3,$A9&"1231",$A9&"1231","Fill=NA","Days=A")} -> 7492 | E9: {=_xll.BDH(E$2,E$3,$A9&"1231",$A9&"1231","Fill=NA","Days=A")} -> 1785 | F9: {=_xll.BDH(F$2,F$3,$A9&"1231",$A9&"1231","Fill=NA","Days=A")} -> 1231 | G9: {=_xll.BDH(G$2,G$3,$A9&"1231",$A9&"1231","Fill=NA","Days=A")} -> 600 | H9: {=_xll.BDH(H$2,H$3,$A9&"1231",$A9&"1231","Fill=NA","Days=A")} -> 4023 | I9: {=_xll.BDH(I$2,I$3,$A9&"1231",$A9&"1231","Fill=NA","Days=A")} -> 53501 | ... Q9: {=_xll.BDH(Q$2,Q$3,$A9&"1231",$A9&"1231","Fill=NA","Days=A")} -> 3922
A10: =A9+1 -> 2023 | B10: {=_xll.BDH(B$2,B$3,$A10&"1231",$A10&"1231","Fill=NA","Days=A")} -> 46875 | C10: {=_xll.BDH(C$2,C$3,$A10&"1231",$A10&"1231","Fill=NA","Days=A")} -> 6801 | D10: {=_xll.BDH(D$2,D$3,$A10&"1231",$A10&"1231","Fill=NA","Days=A")} -> 8537 | E10: {=_xll.BDH(E$2,E$3,$A10&"1231",$A10&"1231","Fill=NA","Days=A")} -> 1736 | F10: {=_xll.BDH(F$2,F$3,$A10&"1231",$A10&"1231","Fill=NA","Days=A")} -> 785 | G10: {=_xll.BDH(G$2,G$3,$A10&"1231",$A10&"1231","Fill=NA","Days=A")} -> 649 | H10: {=_xll.BDH(H$2,H$3,$A10&"1231",$A10&"1231","Fill=NA","Days=A")} -> 5560 | I10: {=_xll.BDH(I$2,I$3,$A10&"1231",$A10&"1231","Fill=NA","Days=A")} -> 54434 | ... Q10: {=_xll.BDH(Q$2,Q$3,$A10&"1231",$A10&"1231","Fill=NA","Days=A")} -> 765
A11: =A10+1 -> 2024 | B11: {=_xll.BDH(B$2,B$3,$A11&"1231",$A11&"1231","Fill=NA","Days=A")} -> 46489 | C11: {=_xll.BDH(C$2,C$3,$A11&"1231",$A11&"1231","Fill=NA","Days=A")} -> 7273 | D11: {=_xll.BDH(D$2,D$3,$A11&"1231",$A11&"1231","Fill=NA","Days=A")} -> 9090 | E11: {=_xll.BDH(E$2,E$3,$A11&"1231",$A11&"1231","Fill=NA","Days=A")} -> 1817 | F11: {=_xll.BDH(F$2,F$3,$A11&"1231",$A11&"1231","Fill=NA","Days=A")} -> 1637 | G11: {=_xll.BDH(G$2,G$3,$A11&"1231",$A11&"1231","Fill=NA","Days=A")} -> 775 | H11: {=_xll.BDH(H$2,H$3,$A11&"1231",$A11&"1231","Fill=NA","Days=A")} -> 5240 | I11: {=_xll.BDH(I$2,I$3,$A11&"1231",$A11&"1231","Fill=NA","Days=A")} -> 62741 | ... Q11: {=_xll.BDH(Q$2,Q$3,$A11&"1231",$A11&"1231","Fill=NA","Days=A")} -> -1895
A12: LTM | B12: =_xll.BDP($B$2,"EST_SALES_LAST_YR") -> 89825.75 | C12: =_xll.BDP($B$2,"TRAIL_12M_OPER_INC") -> 12277 | D12: =_xll.BDP($B$2,"TRAIL_12M_EBITDA") -> 15910 | E12: =_xll.BDP($B$2,"TRAIL_12M_DEPR_AMORT") -> #N/A Invalid Field | F12: =_xll.BDP($B$2,"TRAIL_12M_INC_TAX_EXP") -> 2640 | G12: =_xll.BDP($B$2,"TRAIL_12M_INT_EXP") -> 1786 | H12: =_xll.BDP($B$2,"TRAIL_12M_NET_INC") -> 9033 | I12: =_xll.BDP($B$2,"SHORT_AND_LONG_TERM_DEBT") -> 57108 | J12: =_xll.BDP($B$2,"BS_CASH_NEAR_CASH_ITEM") -> 4579 | K12: =_xll.BDP($B$2,"MINORITY_INTEREST") -> 221 | L12: =_xll.BDP($B$2,"EQY_SH_OUT") -> 2576.52 | M12: =_xll.BDP($B$2,"TOT_COMMON_EQY") -> 32810 | N12: =_xll.BDP($B$2,"BS_TOT_ASSET") -> 127151 | O12: =_xll.BDP($B$2,"TRAIL_12M_CAP_EXPEND") -> -4527 | P12: =_xll.BDP($B$2,"TRAIL_12M_CASH_FROM_OPER") -> 15904 | Q12: =_xll.BDP($B$2,"TRAIL_12M_CHG_WORK_CAP") -> #N/A Invalid Field
A13: FY1 Est | B13: =_xll.BDP($B$2,"BEST_SALES") -> 21392.833 | C13: =_xll.BDP($B$2,"BEST_OPER_INCOME") -> #N/A Invalid Field | D13: =_xll.BDP($B$2,"BEST_EBITDA_MEDIAN") -> 17904 | H13: =_xll.BDP($B$2,"BEST_NET_INCOME") -> 11075.273 | O13: =_xll.BDP($B$2,"BEST_CAPEX") -> -4126.071
A15: HARD COPY — Paste Values from BBG block above
A16: Year | B16: Revenue | C16: EBIT | D16: EBITDA | E16: D&A | F16: Tax Expense | G16: Interest Exp | H16: Net Income | I16: Total Debt | J16: Cash & Equiv | K16: Minority Int | L16: Shares Out | M16: Book Equity | N16: Total Assets | O16: CapEx | P16: CFO | Q16: Chg in NWC
A17: =$T$1 -> 2019 | B17: 47251 | C17: 9344 | D17: 11193 | E17: 1849 | F17: 1448 | G17: 510 | H17: 7637 | I17: 37164 | J17: 7469 | K17: 148 | L17: 2880 | M17: 52035 | N17: 127940 | O17: -2616 | P17: 8075 | Q17: 3697
A18: =A17+1 -> 2020 | B18: 43378 | C18: 6963 | D18: 8720 | E18: 1757 | F18: 1367 | G18: 351 | H18: 6349 | I18: 39339 | J18: 5235 | K18: -5 | L18: 2816.5 | M18: 45695 | N18: 124028 | O18: -3201 | P18: 6991 | Q18: 3931
A19: =A18+1 -> 2021 | B19: 45544 | C19: 4813 | D19: 6582 | E19: 1769 | F19: 1140 | G19: 372 | H19: 10960 | I19: 45816 | J19: 6988 | K19: 190 | L19: 2759.5923 | M19: 53140 | N19: 139142 | O19: -2972 | P19: 6223 | Q19: 6799
A20: =A19+1 -> 2022 | B20: 49022 | C20: 5707 | D20: 7492 | E20: 1785 | F20: 1231 | G20: 600 | H20: 4023 | I20: 53501 | J20: 5511 | K20: 171 | L20: 2668.1414 | M20: 41982 | N20: 135182 | O20: -2723 | P20: 5249 | Q20: 3922
A21: =A20+1 -> 2023 | B21: 46875 | C21: 6801 | D21: 8537 | E21: 1736 | F21: 785 | G21: 649 | H21: 5560 | I21: 54434 | J21: 4816 | K21: 164 | L21: 2621.3063 | M21: 35742 | N21: 126550 | O21: -3053 | P21: 7147 | Q21: 765
A22: =A21+1 -> 2024 | B22: 46489 | C22: 7273 | D22: 9090 | E22: 1817 | F22: 1637 | G22: 775 | H22: 5240 | I22: 62741 | J22: 5556 | K22: 159 | L22: 2572.715 | M22: 35917 | N22: 139264 | O22: -2794 | P22: 6911 | Q22: -1895
A23: LTM | B23: 89825.75 | C23: 12277 | D23: 15910 | E23: #N/A Invalid Field | F23: 2640 | G23: 1786 | H23: 9033 | I23: 57108 | J23: 4579 | K23: 221 | L23: 2576.52 | M23: 32810 | N23: 127151 | O23: -4527 | P23: 15904 | Q23: #N/A Invalid Field
A24: FY1 Est | B24: 21392.833 | C24: #N/A Invalid Field | D24: 17904 | H24: 11075.273 | O24: -4126.071
A26: DERIVED METRICS
A27: Year | B27: Rev YoY% | C27: EBIT Mrg | D27: EBITDA Mrg | E27: D&A/Rev | F27: CapEx/Rev | G27: NWC/Rev | H27: Eff Tax | I27: NOPAT | J27: Inv Cap | K27: ROIC | L27: FCFF | M27: FCFF Mrg
A28: =$T$1 -> 2019 | C28: =IFERROR(C17/B17,"") -> 0.19775243 | D28: =IFERROR(D17/B17,"") -> 0.23688388 | E28: =IFERROR(E17/B17,"") -> 0.039131447 | F28: =IFERROR(ABS(O17)/B17,"") -> 0.055363908 | G28: =IFERROR(Q17/B17,"") -> 0.07824173 | H28: =IFERROR(F17/C17,"") -> 0.15496575 | I28: =IFERROR(C17*(1-H28),"") -> 7896 | J28: =IFERROR(M17+I17-J17,"") -> 81730 | K28: =IFERROR(I28/J28,"") -> 0.096610792 | L28: =IFERROR(I28+E17-ABS(O17)-Q17,"") -> 3432 | M28: =IFERROR(L28/B17,"") -> 0.072633383
A29: =A28+1 -> 2020 | B29: =IFERROR(B18/B17-1,"") -> -0.081966519 | C29: =IFERROR(C18/B18,"") -> 0.16051916 | D29: =IFERROR(D18/B18,"") -> 0.20102356 | E29: =IFERROR(E18/B18,"") -> 0.040504403 | F29: =IFERROR(ABS(O18)/B18,"") -> 0.073793167 | G29: =IFERROR(Q18/B18,"") -> 0.090621974 | H29: =IFERROR(F18/C18,"") -> 0.19632342 | I29: =IFERROR(C18*(1-H29),"") -> 5596 | J29: =IFERROR(M18+I18-J18,"") -> 79799 | K29: =IFERROR(I29/J29,"") -> 0.070126192 | L29: =IFERROR(I29+E18-ABS(O18)-Q18,"") -> 221 | M29: =IFERROR(L29/B18,"") -> 0.0050947485
A30: =A29+1 -> 2021 | B30: =IFERROR(B19/B18-1,"") -> 0.049933146 | C30: =IFERROR(C19/B19,"") -> 0.10567803 | D30: =IFERROR(D19/B19,"") -> 0.14451959 | E30: =IFERROR(E19/B19,"") -> 0.03884156 | F30: =IFERROR(ABS(O19)/B19,"") -> 0.065255577 | G30: =IFERROR(Q19/B19,"") -> 0.14928421 | H30: =IFERROR(F19/C19,"") -> 0.23685851 | I30: =IFERROR(C19*(1-H30),"") -> 3673 | J30: =IFERROR(M19+I19-J19,"") -> 91968 | K30: =IFERROR(I30/J30,"") -> 0.039937804 | L30: =IFERROR(I30+E19-ABS(O19)-Q19,"") -> -4329 | M30: =IFERROR(L30/B19,"") -> -0.09505094
A31: =A30+1 -> 2022 | B31: =IFERROR(B20/B19-1,"") -> 0.076365712 | C31: =IFERROR(C20/B20,"") -> 0.11641712 | D31: =IFERROR(D20/B20,"") -> 0.15282934 | E31: =IFERROR(E20/B20,"") -> 0.036412223 | F31: =IFERROR(ABS(O20)/B20,"") -> 0.055546489 | G31: =IFERROR(Q20/B20,"") -> 0.080004896 | H31: =IFERROR(F20/C20,"") -> 0.21570002 | I31: =IFERROR(C20*(1-H31),"") -> 4476 | J31: =IFERROR(M20+I20-J20,"") -> 89972 | K31: =IFERROR(I31/J31,"") -> 0.049748811 | L31: =IFERROR(I31+E20-ABS(O20)-Q20,"") -> -384 | M31: =IFERROR(L31/B20,"") -> -0.0078332177
A32: =A31+1 -> 2023 | B32: =IFERROR(B21/B20-1,"") -> -0.043796663 | C32: =IFERROR(C21/B21,"") -> 0.145088 | D32: =IFERROR(D21/B21,"") -> 0.18212267 | E32: =IFERROR(E21/B21,"") -> 0.037034667 | F32: =IFERROR(ABS(O21)/B21,"") -> 0.065130667 | G32: =IFERROR(Q21/B21,"") -> 0.01632 | H32: =IFERROR(F21/C21,"") -> 0.1154242 | I32: =IFERROR(C21*(1-H32),"") -> 6016 | J32: =IFERROR(M21+I21-J21,"") -> 85360 | K32: =IFERROR(I32/J32,"") -> 0.070477976 | L32: =IFERROR(I32+E21-ABS(O21)-Q21,"") -> 3934 | M32: =IFERROR(L32/B21,"") -> 0.083925333
A33: =A32+1 -> 2024 | B33: =IFERROR(B22/B21-1,"") -> -0.0082346667 | C33: =IFERROR(C22/B22,"") -> 0.15644561 | D33: =IFERROR(D22/B22,"") -> 0.19553013 | E33: =IFERROR(E22/B22,"") -> 0.039084515 | F33: =IFERROR(ABS(O22)/B22,"") -> 0.060100239 | G33: =IFERROR(Q22/B22,"") -> -0.040762331 | H33: =IFERROR(F22/C22,"") -> 0.22507906 | I33: =IFERROR(C22*(1-H33),"") -> 5636 | J33: =IFERROR(M22+I22-J22,"") -> 93102 | K33: =IFERROR(I33/J33,"") -> 0.060535756 | L33: =IFERROR(I33+E22-ABS(O22)-Q22,"") -> 6554 | M33: =IFERROR(L33/B22,"") -> 0.14097959
A35: SUMMARY
A36: 5Y Rev CAGR | B36: =IFERROR((B22/B17)^(1/6)-1,"") -> -0.0027060142
A37: 3Y Rev CAGR | B37: =IFERROR((B22/B19)^(1/3)-1,"") -> 0.006869096
A38: Med EBIT Mrg | B38: =IFERROR(MEDIAN(C28:C33),"") -> 0.15076681
A39: Med ROIC | B39: =IFERROR(MEDIAN(K28:K33),"") -> 0.065330974
A40: Avg Eff Tax | B40: =IFERROR(AVERAGE(H28:H33),"") -> 0.19072516
A41: Avg FCFF Mrg | B41: =IFERROR(AVERAGE(M28:M33),"") -> 0.033291482
A42: Max Rev Gr | B42: =IFERROR(MAX(B29:B33),"") -> 0.076365712
A43: Min Rev Gr | B43: =IFERROR(MIN(B29:B33),"") -> -0.081966519

Sheet Current
A1: Ticker: | B1: =Fundamentals!B2 -> NESN SW Equity
A3: Field | B3: BBG Live | C3: Hard Copy | D3: BBG Field
A4: Price | B4: =_xll.BDP($B$1,"PX_LAST") -> 77.62 | C4: 77.62 | D4: PX_LAST
A5: Market Cap | B5: =_xll.BDP($B$1,"CUR_MKT_CAP") -> 199989482400 | C5: 199989482400 | D5: CUR_MKT_CAP
A6: Shares Out | B6: =_xll.BDP($B$1,"EQY_SH_OUT") -> 2576.52 | C6: 2576.52 | D6: EQY_SH_OUT
A7: EV | B7: =_xll.BDP($B$1,"ENTERPRISE_VALUE") -> 253662.98 | C7: 253662.98 | D7: ENTERPRISE_VALUE
A8: Beta Raw | B8: =_xll.BDP($B$1,"BETA_RAW_OVERRIDABLE") -> 0.7762176 | C8: 0.7762176 | D8: BETA_RAW_OVERRIDABLE
A9: Beta Adj | B9: =_xll.BDP($B$1,"BETA_ADJ_OVERRIDABLE") -> 0.8508032 | C9: 0.8508032 | D9: BETA_ADJ_OVERRIDABLE
A10: BBG WACC | B10: =_xll.BDP($B$1,"WACC") -> 5.8425363 | C10: 5.8425363 | D10: WACC
A11: ROIC | B11: =_xll.BDP($B$1,"RETURN_ON_INV_CAPITAL") -> 10.229177 | C11: 10.229177 | D11: RETURN_ON_INV_CAPITAL
A12: Div Yield | B12: =_xll.BDP($B$1,"EQY_DVD_YLD_12M") -> 3.9293996 | C12: 3.9293996 | D12: EQY_DVD_YLD_12M
A13: D/E | B13: =_xll.BDP($B$1,"TOT_DEBT_TO_TOT_EQY") -> 172.75092 | C13: 172.75092 | D13: TOT_DEBT_TO_TOT_EQY
A14: Op Margin | B14: =_xll.BDP($B$1,"OPER_MARGIN") -> 13.658564 | C14: 13.658564 | D14: OPER_MARGIN
A15: Cons Rev FY1 | B15: =_xll.BDP($B$1,"BEST_SALES") -> 21392.833 | C15: 21392.833 | D15: BEST_SALES
A16: Cons EPS FY1 | B16: =_xll.BDP($B$1,"BEST_EPS") -> 4.344 | C16: 4.344 | D16: BEST_EPS
A18: DERIVED
A19: Net Debt | C19: =Fundamentals!I22-Fundamentals!J22 -> 57185
A20: Minority Int | C20: =Fundamentals!K22 -> 159
A21: EV calc | C21: =C5+C19+C20 -> 199989539744

Sheet Macro
A1: MACRO
A3: Region | B3: Ticker | C3: BBG Live | D3: Hard Copy
A4: Switzerland | B4: GSWISS10 Index | C4: =_xll.BDP("GSWISS10 Index","PX_LAST")/100 -> 0.004 | D4: 0.004
A5: Eurozone | B5: GDBR10 Index | C5: =_xll.BDP("GDBR10 Index","PX_LAST")/100 -> 0.02997 | D5: 0.02997
A6: USA | B6: USGG10YR Index | C6: =_xll.BDP("USGG10YR Index","PX_LAST")/100 -> 0.042945 | D6: 0.042945
A7: UK | B7: GUKG10 Index | C7: =_xll.BDP("GUKG10 Index","PX_LAST")/100 -> 0.0486 | D7: 0.0486
A8: Japan | B8: JGBS10 Index | C8: =_xll.BDP("JGBS10 Index","PX_LAST")/100 -> 0.02231 | D8: 0.02231
A10: GDP
A11: Region | B11: Real | C11: Infl | D11: Nominal
A12: Switzerland | B12: 0.015 | C12: 0.01 | D12: =IFERROR((1+B12)*(1+C12)-1,"") -> 0.02515
A13: Eurozone | B13: 0.012 | C13: 0.02 | D13: =IFERROR((1+B13)*(1+C13)-1,"") -> 0.03224
A14: USA | B14: 0.02 | C14: 0.025 | D14: =IFERROR((1+B14)*(1+C14)-1,"") -> 0.0455
A15: UK | B15: 0.015 | C15: 0.02 | D15: =IFERROR((1+B15)*(1+C15)-1,"") -> 0.0353
A16: Japan | B16: 0.008 | C16: 0.015 | D16: =IFERROR((1+B16)*(1+C16)-1,"") -> 0.02312
A17: EM | B17: 0.04 | C17: 0.035 | D17: =IFERROR((1+B17)*(1+C17)-1,"") -> 0.0764
A19: ERP
A20: Source | B20: ERP
A21: Damodaran | B21: 0.048
A22: DMS | B22: 0.05
A23: Own/IC | B23: 0.055

Sheet WACC
A1: WACC
A3: Param | B3: Linked | C3: Manual | D3: Active | E3: Used | F3: Note
A4: Rf | B4: =Macro!D4 -> 0.004 | C4: 0.008 | D4: Linked | E4: =IFERROR(IF(D4="Manual",C4,B4),C4) -> 0.004 | F4: Macro HC
A5: ERP | B5: =Macro!B23 -> 0.055 | C5: 0.055 | D5: Linked | E5: =IFERROR(IF(D5="Manual",C5,B5),C5) -> 0.055 | F5: Macro
A6: Beta | B6: =Current!C9 -> 0.8508032 | C6: 0.7 | D6: Linked | E6: =IFERROR(IF(D6="Manual",C6,B6),C6) -> 0.8508032 | F6: Current HC
A7: CoE | D7: Calc | E7: =IFERROR(E4+E6*E5,"") -> 0.050794176 | F7: Rf+B*ERP
A8: Pre-Tax CoD | C8: 0.015 | D8: Manual | E8: =IFERROR(IF(D8="Manual",C8,B8),C8) -> 0.015 | F8: Manual
A9: Tax Rate | B9: =Fundamentals!B40 -> 0.19072516 | C9: 0.22 | D9: Linked | E9: =IFERROR(IF(D9="Manual",C9,B9),C9) -> 0.19072516 | F9: Fund avg
A10: AT CoD | D10: Calc | E10: =IFERROR(E8*(1-E9),"") -> 0.012139123 | F10: CoD*(1-t)
A11: Eq Weight | C11: 0.87 | D11: Manual | E11: =IFERROR(IF(D11="Manual",C11,B11),C11) -> 0.87 | F11: E/(D+E)
A12: Debt Wt | D12: Calc | E12: =IFERROR(1-E11,"") -> 0.13 | F12: 1-EqWt
A13: WACC | D13: Calc | E13: =IFERROR(E11*E7+E12*E10,"") -> 0.045769019 | F13: Result
A14: Tg | B14: =Macro!D12 -> 0.02515 | C14: 0.02 | D14: Linked | E14: =IFERROR(IF(D14="Manual",C14,B14),C14) -> 0.02515 | F14: GDP
A15: T Margin | B15: =Fundamentals!B38 -> 0.15076681 | C15: 0.15 | D15: Linked | E15: =IFERROR(IF(D15="Manual",C15,B15),C15) -> 0.15076681 | F15: Median
A16: Proj Yrs | C16: 5 | D16: Manual | E16: =IFERROR(IF(D16="Manual",C16,B16),C16) -> 5
A17: Bull | C17: 0.03 | D17: Manual | E17: =IFERROR(IF(D17="Manual",C17,B17),C17) -> 0.03 | F17: +pp
A18: Bear | C18: -0.03 | D18: Manual | E18: =IFERROR(IF(D18="Manual",C18,B18),C18) -> -0.03 | F18: -pp

Sheet Instructions
A1: WORKFLOW
A3: 1. Change ticker in Fundamentals!B2
A4: 2. Each cell B6:Q11 has its own BDH (semicolons, fix date pair)
A5: Example: =BDH(B$2;B$3;"20191231";"20191231";"Fill=NA";"Days=A")
A6: 3. LTM (row 12) + FY1 Est (row 13): BDP formulas
A7: 4. Copy B6:Q13 → Paste Values into B17:Q24
A8: 5. To add 2025: insert row before LTM, type year, write BDH with "20251231"
A9: 6. Current: Copy col B → col C | Macro: Copy col C → col D
A10: 7. WACC: Auto-links. Active='Manual' to override.
A11: 8. Save → streamlit run app.py → upload
